dveo/__init__.py
dveo/api.py
dveo/utils.py
dveo-0.2.1.dist-info/METADATA
dveo-0.2.1.dist-info/RECORD
dveo-0.2.1.dist-info/WHEEL
dveo-0.2.1.dist-info/top_level.txt
