Metadata-Version: 2.1
Name: dveo
Version: 0.2.1
Summary: DVEO REST API wrapper
Home-page: https://github.com/madeddie/dveo
Author: Edwin Hermans
Author-email: edwin@madtech.cx
License: UNKNOWN
Project-URL: Bug Reports, https://github.com/madeddie/dveo/issues
Project-URL: Source, https://github.com/madeddie/dveo/
Keywords: dveo video encoder api
Platform: UNKNOWN
Classifier: Development Status :: 4 - Beta
Classifier: Intended Audience :: Developers
Classifier: License :: OSI Approved :: MIT License
Classifier: Programming Language :: Python :: 3
Classifier: Programming Language :: Python :: 3.4
Classifier: Programming Language :: Python :: 3.5
Classifier: Programming Language :: Python :: 3.6
Classifier: Programming Language :: Python :: 3.7
Provides-Extra: dev
Requires-Dist: requests
Requires-Dist: xmltodict
Provides-Extra: dev
Requires-Dist: black; extra == 'dev'
Requires-Dist: flake8; extra == 'dev'
Requires-Dist: rope; extra == 'dev'
Requires-Dist: pydocstyle; extra == 'dev'
Requires-Dist: sphinx; extra == 'dev'
